hf_cli.py
hf_cli-0.1.dist-info/METADATA
hf_cli-0.1.dist-info/WHEEL
hf_cli-0.1.dist-info/entry_points.txt
hf_cli-0.1.dist-info/top_level.txt
hf_cli-0.1.dist-info/RECORD
